xlearn/VERSION
xlearn/__init__.py
xlearn/_sklearn.py
xlearn/base.py
xlearn/libpath.py
xlearn/xlearn.py
xlearntestbyamshoreline-1.0.data/data/xlearn/libxlearn_api.so
xlearntestbyamshoreline-1.0.dist-info/METADATA
xlearntestbyamshoreline-1.0.dist-info/RECORD
xlearntestbyamshoreline-1.0.dist-info/WHEEL
xlearntestbyamshoreline-1.0.dist-info/top_level.txt
