Metadata-Version: 2.1
Name: xlearntestbyamshoreline
Version: 1.0
Summary: xLearn Python Package
Home-page: https://github.com/aksnzhy/xlearn
Author: Chao Ma
Author-email: mctt90@gmail.com
License: Apache-2.0
Platform: UNKNOWN
Classifier: License :: OSI Approved :: Apache Software License
